project/m2/rtl/compute_core.sv
// Simple compute core (MAC unit)
// Synchronous, active-high reset

module compute_core (
    input logic clk,
    input logic rst,
    input logic signed [7:0] a,
    input logic signed [7:0] b,
    input logic valid_in,
    output logic signed [31:0] out,
    output logic valid_out
);

    always_ff @(posedge clk) begin
        if (rst) begin
            out <= 0;
            valid_out <= 0;
        end else begin
            if (valid_in) begin
                out <= out + (a * b);
                valid_out <= 1;
            end else begin
                valid_out <= 0;
            end
        end
    end

endmodule

project/m2/tb/tb_compute_core.sv
module tb_compute_core;

    logic clk;
    logic rst;
    logic signed [7:0] a, b;
    logic valid_in;
    logic signed [31:0] out;
    logic valid_out;

    compute_core uut (
        .clk(clk),
        .rst(rst),
        .a(a),
        .b(b),
        .valid_in(valid_in),
        .out(out),
        .valid_out(valid_out)
    );

    always #5 clk = ~clk;

    initial begin
        $dumpfile("sim/wave.vcd");
        $dumpvars(0, tb_compute_core);
        clk = 0;
        rst = 1;
        valid_in = 0;
        a = 0;
        b = 0;

        #10 rst = 0;

        #10 a = 3; b = 4; valid_in = 1;
        #10 valid_in = 0;

        #10 a = -5; b = 2; valid_in = 1;
        #10 valid_in = 0;
        #10;
        if (out == ((3*4) + (-5*2))) begin
            $display("PASS");
        end else begin
             $display("FAIL");
        end
        #50 $finish;
    end

endmodule

project/m2/sim/wave.vcd
$date
	Mon May  4 02:21:02 2026
$end
$version
	Icarus Verilog
$end
$timescale
	1s
$end
$scope module tb_compute_core $end
$var wire 1 ! valid_out $end
$var wire 32 " out [31:0] $end
$var reg 8 # a [7:0] $end
$var reg 8 $ b [7:0] $end
$var reg 1 % clk $end
$var reg 1 & rst $end
$var reg 1 ' valid_in $end
$scope module uut $end
$var wire 8 ( a [7:0] $end
$var wire 8 ) b [7:0] $end
$var wire 1 % clk $end
$var wire 1 & rst $end
$var wire 1 ' valid_in $end
$var reg 32 * out [31:0] $end
$var reg 1 ! valid_out $end
$upscope $end
$upscope $end
$enddefinitions $end
$comment Show the parameter values. $end
$dumpall
$end
#0
$dumpvars
bx *
b0 )
b0 (
0'
1&
0%
b0 $
b0 #
bx "
x!
$end
#5
0!
b0 "
b0 *
1%
#10
0%
0&
#15
1%
#20
0%
1'
b100 $
b100 )
b11 #
b11 (
#25
1!
b1100 "
b1100 *
1%
#30
0%
0'
#35
0!
1%
#40
0%
1'
b10 $
b10 )
b11111011 #
b11111011 (
#45
1!
b10 "
b10 *
1%
#50
0%
0'
#55
0!
1%
